mcp_stock_calculator/__init__.py
mcp_stock_calculator/__main__.py
mcp_stock_calculator/calculator.py
mcp_stock_calculator/server.py
mcp_stock_calculator-0.1.2.dist-info/METADATA
mcp_stock_calculator-0.1.2.dist-info/WHEEL
mcp_stock_calculator-0.1.2.dist-info/entry_points.txt
mcp_stock_calculator-0.1.2.dist-info/top_level.txt
mcp_stock_calculator-0.1.2.dist-info/RECORD
