Metadata-Version: 2.4
Name: mcp_stock_calculator
Version: 0.1.2
Summary: A股技术指标计算器 - 提供MACD, RSI, KDJ, BOLL等常用技术指标计算
Home-page: https://github.com/yorkqqcom/mcp_stock_calculator
Author: YORK
Author-email: 27123167@qq.com
Keywords: stock,technical indicator,a-share,chinese stock,finance
Classifier: Programming Language :: Python :: 3
Classifier: License :: OSI Approved :: MIT License
Classifier: Operating System :: OS Independent
Classifier: Topic :: Office/Business :: Financial
Classifier: Topic :: Office/Business :: Financial :: Investment
Classifier: Development Status :: 4 - Beta
Requires-Python: >=3.7
Requires-Dist: flask>=2.0.0
Requires-Dist: pandas>=1.0.0
Requires-Dist: numpy>=1.18.0
Requires-Dist: akshare>=1.0.0
Dynamic: author
Dynamic: author-email
Dynamic: classifier
Dynamic: description
Dynamic: description-content-type
Dynamic: home-page
Dynamic: keywords
Dynamic: requires-dist
Dynamic: requires-python
Dynamic: summary
